[
  {
    "name": "MV-Si002 お試しサイズ 500mg - 112003",
    "slug": "trial-112003",
    "description": "1g - 約30日分",
    "originalprice": "3,300円",
    "price": "2,200円",
    "ItemPic": "/trial.png",
    "wixProductId": "8ed88eab-e077-4f74-ac69-6189b5903323",
    "url": "https://www.dotpb.jp/product-page/trial-112003"
  },
  {
    "name": "MV-Si002 スタンダードサイズ 2,000mg - 112003",
    "slug": "standard-112003",
    "description": "2g - 約60日分",
    "originalprice": "6,600円",
    "price": "3,600円",
    "ItemPic": "/standard.png",
    "wixProductId": "8da9fa99-6ecf-4dda-b8fc-f46efefa5d27",
    "url": "https://www.dotpb.jp/product-page/standard-112003"
  },
  {
    "name": "MV-Si002 お得な大容量 5,000mg - 112003",
    "slug": "large-112003",
    "description": "35g - 約150日分",
    "originalprice": "11,000円",
    "price": "7,400円",
    "ItemPic": "/large.png",
    "wixProductId": "c3ed0cf8-d1aa-4654-8386-3d66ea6a1de2",
    "url": "https://www.dotpb.jp/product-page/large-112003"
  }
]