[
  {
    "name": "MV-Si002 お試しサイズ 500mg - 141302",
    "slug": "trial-141302",
    "description": "1g - 約30日分",
    "originalprice": "3,300円",
    "price": "2,200円",
    "ItemPic": "/trial.png",
    "wixProductId": "7a8aa3b7-9f7b-4613-b071-cef3bc5f0d2c",
    "url": "https://www.dotpb.jp/product-page/trial-141302"
  },
  {
    "name": "MV-Si002 スタンダードサイズ 2,000mg - 141302",
    "slug": "standard-141302",
    "description": "2g - 約60日分",
    "originalprice": "6,600円",
    "price": "3,600円",
    "ItemPic": "/standard.png",
    "wixProductId": "bf85ffee-3cfc-473a-80fe-ff4fe2fec8ea",
    "url": "https://www.dotpb.jp/product-page/standard-141302"
  },
  {
    "name": "MV-Si002 お得な大容量 5,000mg - 141302",
    "slug": "large-141302",
    "description": "35g - 約150日分",
    "originalprice": "11,000円",
    "price": "7,400円",
    "ItemPic": "/large.png",
    "wixProductId": "1c6b76ec-637f-425c-8d4c-9902367ad893",
    "url": "https://www.dotpb.jp/product-page/large-141302"
  }
]