[
  {
    "name": "MV-Si002 お得な大容量 5,000mg - 1511",
    "slug": "large-1511",
    "description": "35g - 約150日分",
    "originalprice": "11,000円",
    "price": "8,000円",
    "ItemPic": "/large.png",
    "wixProductId": "d8309f23-73e0-4835-a73a-fb1c8be1a4ce",
    "url": "https://www.dotpb.jp/product-page/large-1511"
  },
  {
    "name": "MV-Si002 お試しサイズ 500mg - 1511",
    "slug": "trial-1511",
    "description": "1g - 約30日分",
    "originalprice": "3,300円",
    "price": "2,000円",
    "ItemPic": "/trial.png",
    "wixProductId": "5b41281f-458c-4933-8a77-00fdb34ec0a6",
    "url": "https://www.dotpb.jp/product-page/trial-1511"
  },
  {
    "name": "MV-Si002 スタンダードサイズ 2,000mg - 1511",
    "slug": "standard-1511",
    "description": "2g - 約60日分",
    "originalprice": "6,600円",
    "price": "4,000円",
    "ItemPic": "/standard.png",
    "wixProductId": "f4a5ec28-7540-4ca0-b5f8-5f55cc664aae",
    "url": "https://www.dotpb.jp/product-page/standard-1511"
  },
  {
    "name": "PBスキンパウダー：【30本セット】マザベジシリカパウダー 30,000mg（エクトイン入り） -1511",
    "slug": "big-refill-e-1511",
    "description": "30本セットです。",
    "originalprice": "30,800円",
    "price": "28,000円",
    "ItemPic": "/big-refill-e.png",
    "wixProductId": "e01ece4e-a4de-4dab-8616-6381128b0658",
    "url": "https://www.dotpb.jp/product-page/big-refill-e-1511"
  },
  {
    "name": "PBスキンパウダー：【10本セット】マザベジシリカパウダー 10,000mg（エクトイン入り） -1511",
    "slug": "refill-e-1511",
    "description": "10本セットです。",
    "originalprice": "12,100円",
    "price": "11,000円",
    "ItemPic": "/refill-e.png",
    "wixProductId": "f526c14f-7dd8-4804-9455-3546c1dc7fce",
    "url": "https://www.dotpb.jp/product-page/refill-e-1511"
  },
  {
    "name": "PBスキンパウダー：【薬用スライドケース】マザベジシリカパウダー 2,000mg（エクトイン入り） -1511",
    "slug": "case-e-1511",
    "description": "薬用スライドケ－スです。",
    "originalprice": "3,410円",
    "price": "3,100円",
    "ItemPic": "/case-e.png",
    "wixProductId": "41b89e94-de5b-4645-943d-6ed036228c62",
    "url": "https://www.dotpb.jp/product-page/case-e-1511"
  },
  {
    "name": "PBスキンパウダー：【30本セット】マザベジシリカパウダー 22,500mg -1511",
    "slug": "big-refill-1511",
    "description": "30本セットです。",
    "originalprice": "19,800円",
    "price": "18,000円",
    "ItemPic": "/big-refill.png",
    "wixProductId": "26c2b082-e53f-4fd8-8a63-53398ceda727",
    "url": "https://www.dotpb.jp/product-page/big-refill-1511"
  },
  {
    "name": "PBスキンパウダー： 【ミックスパック】 マザベジシリカパウダー 1,500mg -1511",
    "slug": "double-1511",
    "description": "ミックスパックです。",
    "originalprice": "3,410円",
    "price": "3,100円",
    "ItemPic": "/double.png",
    "wixProductId": "a1f815a8-a24a-4e09-9929-808a4be41cb3",
    "url": "https://www.dotpb.jp/product-page/double-1511"
  },
  {
    "name": "PBスキンパウダー：【薬用スライドケース】マザベジシリカパウダー 1,500mg -1511",
    "slug": "case-1511",
    "description": "薬用スライドケ－スです。",
    "originalprice": "3,410円",
    "price": "3,100円",
    "ItemPic": "/case.png",
    "wixProductId": "dffa0472-3c32-4d23-a4a3-fd2cac3754bf",
    "url": "https://www.dotpb.jp/product-page/case-1511"
  },
  {
    "name": "PBスキンパウダー：【ミックスパック】 マザベジシリカパウダー 2,000mg（エクトイン入り） -1511",
    "slug": "double-e-1511",
    "description": "ミックスパックです。",
    "originalprice": "3,410円",
    "price": "3,100円",
    "ItemPic": "/double-e.png",
    "wixProductId": "876ffda5-9ef7-462a-8228-29bf2d6ac96d",
    "url": "https://www.dotpb.jp/product-page/double-e-1511"
  }
]